pyscored/__init__.py
pyscored/adapters/__init__.py
pyscored/adapters/game_frameworks.py
pyscored/adapters/web_frameworks.py
pyscored/core/__init__.py
pyscored/core/sandbox.py
pyscored/core/scoring_engine.py
pyscored/plugins/__init__.py
pyscored/plugins/base_plugin.py
pyscored/plugins/combo_bonus_plugin.py
pyscored/plugins/time_decay_plugin.py
pyscored/utils/__init__.py
pyscored/utils/helpers.py
pyscored-0.1.1.dist-info/LICENSE
pyscored-0.1.1.dist-info/METADATA
pyscored-0.1.1.dist-info/WHEEL
pyscored-0.1.1.dist-info/RECORD
