Metadata-Version: 2.3
Name: pyscored
Version: 0.1.1
Summary: Universal, Plug-in-Play Scoring System
License: GNU
Author: Ericson Willians
Author-email: ericsonwillians@protonmail.com
Requires-Python: >=3.8,<4.0
Classifier: Development Status :: 3 - Alpha
Classifier: Intended Audience :: Developers
Classifier: License :: OSI Approved :: MIT License
Classifier: License :: Other/Proprietary License
Classifier: Programming Language :: Python :: 3
Classifier: Programming Language :: Python :: 3.8
Classifier: Programming Language :: Python :: 3.9
Classifier: Programming Language :: Python :: 3.10
Classifier: Programming Language :: Python :: 3.11
Classifier: Programming Language :: Python :: 3.12
Classifier: Programming Language :: Python :: 3.13
Project-URL: Documentation, https://github.com/ericsonwillians/pyscored/docs/API.md
Project-URL: Repository, https://github.com/ericsonwillians/pyscored
